Workbook

Sheet Assumptions
A1: AvaCoin Daily-Allowance Model — Assumptions
A3: Input | B3: Value | C3: Note
A4: Coin value (USD per coin) | B4: 0.01 | C4: CANONICAL: wallet.ts COINS_PER_USD=100 → 1 coin=$0.01 (fix feature_pricing 1000/USD bug)
A5: Daily free allowance (coins) | B5: 1000 | C5: Premium daily budget; exhaust → fall back to basic till 00:00 UTC reset
A6: Alt allowance to test (coins) | B6: 500 | C6: Scenario lever
A7: Total users | B7: 1000 | C7: Planning horizon
A8: Daily active % (DAU) | B8: 0.4 | C8: Share of users active on a given day

Sheet Per-Feature
A1: Cost per feature (our cost-to-us vs coin price; what 1,000 coins buys)
A3: Feature | B3: Coin price | C3: Unit | D3: Our cost LOW ($) | E3: Our cost HIGH ($) | F3: USD charged | G3: Actions / allowance | H3: Our $ if ALL allowance here (LOW) | I3: Our $ (HIGH) | J3: Margin (x, mid) | K3: Pool?
A4: Text chat (Gemma 4 / Workers AI) | B4: 2 | C4: msg | D4: 0.0005 | E4: 0.0005 | F4: =B4*Assumptions!$B$4 -> 0.02 | G4: =IF(B4=0,"—",Assumptions!$B$5/B4) -> 500 | H4: =IF(B4=0,0,(Assumptions!$B$5/B4)*D4) -> 0.25 | I4: =IF(B4=0,0,(Assumptions!$B$5/B4)*E4) -> 0.25 | J4: =IF((D4+E4)=0,"—",F4/((D4+E4)/2)) -> 40 | K4: Pooled
A5: Image — free tier (Flux schnell) | B5: 5 | C5: img | D5: 0.0006 | E5: 0.0006 | F5: =B5*Assumptions!$B$4 -> 0.05 | G5: =IF(B5=0,"—",Assumptions!$B$5/B5) -> 200 | H5: =IF(B5=0,0,(Assumptions!$B$5/B5)*D5) -> 0.12 | I5: =IF(B5=0,0,(Assumptions!$B$5/B5)*E5) -> 0.12 | J5: =IF((D5+E5)=0,"—",F5/((D5+E5)/2)) -> 83.333333 | K5: Pooled
A6: Image — paid (Nano Banana 2) | B6: 80 | C6: img | D6: 0.04 | E6: 0.067 | F6: =B6*Assumptions!$B$4 -> 0.8 | G6: =IF(B6=0,"—",Assumptions!$B$5/B6) -> 12.5 | H6: =IF(B6=0,0,(Assumptions!$B$5/B6)*D6) -> 0.5 | I6: =IF(B6=0,0,(Assumptions!$B$5/B6)*E6) -> 0.8375 | J6: =IF((D6+E6)=0,"—",F6/((D6+E6)/2)) -> 14.953271 | K6: Sub-cap
A7: Voice reply (on-device TTS) | B7: 20 | C7: reply | D7: 0 | E7: 0.002 | F7: =B7*Assumptions!$B$4 -> 0.2 | G7: =IF(B7=0,"—",Assumptions!$B$5/B7) -> 50 | H7: =IF(B7=0,0,(Assumptions!$B$5/B7)*D7) -> 0 | I7: =IF(B7=0,0,(Assumptions!$B$5/B7)*E7) -> 0.1 | J7: =IF((D7+E7)=0,"—",F7/((D7+E7)/2)) -> 200 | K7: Pooled
A8: Vision snapshot (Gemini 3 Flash) | B8: 10 | C8: snap | D8: 0.014 | E8: 0.05 | F8: =B8*Assumptions!$B$4 -> 0.1 | G8: =IF(B8=0,"—",Assumptions!$B$5/B8) -> 100 | H8: =IF(B8=0,0,(Assumptions!$B$5/B8)*D8) -> 1.4 | I8: =IF(B8=0,0,(Assumptions!$B$5/B8)*E8) -> 5 | J8: =IF((D8+E8)=0,"—",F8/((D8+E8)/2)) -> 3.125 | K8: Sub-cap
A9: Composio / MCP tool call | B9: 10 | C9: call | D9: 0.0002 | E9: 0.0003 | F9: =B9*Assumptions!$B$4 -> 0.1 | G9: =IF(B9=0,"—",Assumptions!$B$5/B9) -> 100 | H9: =IF(B9=0,0,(Assumptions!$B$5/B9)*D9) -> 0.02 | I9: =IF(B9=0,0,(Assumptions!$B$5/B9)*E9) -> 0.03 | J9: =IF((D9+E9)=0,"—",F9/((D9+E9)/2)) -> 400 | K9: Pooled
A10: GenUI render (Gemini Flash) | B10: 10 | C10: render | D10: 0.001 | E10: 0.005 | F10: =B10*Assumptions!$B$4 -> 0.1 | G10: =IF(B10=0,"—",Assumptions!$B$5/B10) -> 100 | H10: =IF(B10=0,0,(Assumptions!$B$5/B10)*D10) -> 0.1 | I10: =IF(B10=0,0,(Assumptions!$B$5/B10)*E10) -> 0.5 | J10: =IF((D10+E10)=0,"—",F10/((D10+E10)/2)) -> 33.333333 | K10: Pooled
A11: Live translation | B11: 5 | C11: min | D11: 0.017 | E11: 0.033 | F11: =B11*Assumptions!$B$4 -> 0.05 | G11: =IF(B11=0,"—",Assumptions!$B$5/B11) -> 200 | H11: =IF(B11=0,0,(Assumptions!$B$5/B11)*D11) -> 3.4 | I11: =IF(B11=0,0,(Assumptions!$B$5/B11)*E11) -> 6.6 | J11: =IF((D11+E11)=0,"—",F11/((D11+E11)/2)) -> 2 | K11: Sub-cap
A12: AI voice call (Gemini Live) | B12: 17 | C12: min | D12: 0.013 | E12: 0.022 | F12: =B12*Assumptions!$B$4 -> 0.17 | G12: =IF(B12=0,"—",Assumptions!$B$5/B12) -> 58.823529 | H12: =IF(B12=0,0,(Assumptions!$B$5/B12)*D12) -> 0.76470588 | I12: =IF(B12=0,0,(Assumptions!$B$5/B12)*E12) -> 1.2941176 | J12: =IF((D12+E12)=0,"—",F12/((D12+E12)/2)) -> 9.7142857 | K12: Sub-cap
A13: Receptionist (2-min Gemini Live) | B13: 35 | C13: call | D13: 0.035 | E13: 0.05 | F13: =B13*Assumptions!$B$4 -> 0.35 | G13: =IF(B13=0,"—",Assumptions!$B$5/B13) -> 28.571429 | H13: =IF(B13=0,0,(Assumptions!$B$5/B13)*D13) -> 1 | I13: =IF(B13=0,0,(Assumptions!$B$5/B13)*E13) -> 1.4285714 | J13: =IF((D13+E13)=0,"—",F13/((D13+E13)/2)) -> 8.2352941 | K13: Sub-cap
A14: Group conference (LiveKit) | B14: 1 | C14: part-min | D14: 0.0005 | E14: 0.0005 | F14: =B14*Assumptions!$B$4 -> 0.01 | G14: =IF(B14=0,"—",Assumptions!$B$5/B14) -> 1000 | H14: =IF(B14=0,0,(Assumptions!$B$5/B14)*D14) -> 0.5 | I14: =IF(B14=0,0,(Assumptions!$B$5/B14)*E14) -> 0.5 | J14: =IF((D14+E14)=0,"—",F14/((D14+E14)/2)) -> 20 | K14: Free infra
A15: 1:1 P2P call (Cloudflare TURN) | B15: 0 | C15: min | D15: 0 | E15: 0.001 | F15: =B15*Assumptions!$B$4 -> 0 | G15: =IF(B15=0,"—",Assumptions!$B$5/B15) -> — | H15: =IF(B15=0,0,(Assumptions!$B$5/B15)*D15) -> 0 | I15: =IF(B15=0,0,(Assumptions!$B$5/B15)*E15) -> 0 | J15: =IF((D15+E15)=0,"—",F15/((D15+E15)/2)) -> 0 | K15: Free infra
A16: Messaging (InboxDO + R2) | B16: 0 | C16: msg | D16: 1e-05 | E16: 0.0001 | F16: =B16*Assumptions!$B$4 -> 0 | G16: =IF(B16=0,"—",Assumptions!$B$5/B16) -> — | H16: =IF(B16=0,0,(Assumptions!$B$5/B16)*D16) -> 0 | I16: =IF(B16=0,0,(Assumptions!$B$5/B16)*E16) -> 0 | J16: =IF((D16+E16)=0,"—",F16/((D16+E16)/2)) -> 0 | K16: Free infra

Sheet Scenarios
A1: Scenarios — worst case, realistic basket, 1,000-user projection
A3: A) Worst case: a user spends ALL daily coins on the single most expensive feature
A4: Most expensive single feature → our cost/day (HIGH) | B4: =MAX('Per-Feature'!I4:I16) -> 6.6 | C4: ⚠ This is Live Translation — why expensive real-time AI needs per-feature sub-caps
A5: …per month | B5: =B4*30 -> 198
A7: B) Realistic basket per ACTIVE user/day (edit the blue counts)
A8: Feature | B8: Actions/day | C8: Coin price (link) | D8: Coins used | E8: Our $ LOW | F8: Our $ HIGH
A9: Text chat (Gemma 4 / Workers AI) | B9: 40 | C9: ='Per-Feature'!B4 -> 2 | D9: =B9*C9 -> 80 | E9: =B9*'Per-Feature'!D4 -> 0.02 | F9: =B9*'Per-Feature'!E4 -> 0.02
A10: Image — paid (Nano Banana 2) | B10: 1 | C10: ='Per-Feature'!B6 -> 80 | D10: =B10*C10 -> 80 | E10: =B10*'Per-Feature'!D6 -> 0.04 | F10: =B10*'Per-Feature'!E6 -> 0.067
A11: Vision snapshot (Gemini 3 Flash) | B11: 1 | C11: ='Per-Feature'!B8 -> 10 | D11: =B11*C11 -> 10 | E11: =B11*'Per-Feature'!D8 -> 0.014 | F11: =B11*'Per-Feature'!E8 -> 0.05
A12: Composio / MCP tool call | B12: 5 | C12: ='Per-Feature'!B9 -> 10 | D12: =B12*C12 -> 50 | E12: =B12*'Per-Feature'!D9 -> 0.001 | F12: =B12*'Per-Feature'!E9 -> 0.0015
A13: GenUI render (Gemini Flash) | B13: 3 | C13: ='Per-Feature'!B10 -> 10 | D13: =B13*C13 -> 30 | E13: =B13*'Per-Feature'!D10 -> 0.003 | F13: =B13*'Per-Feature'!E10 -> 0.015
A14: Live translation | B14: 3 | C14: ='Per-Feature'!B11 -> 5 | D14: =B14*C14 -> 15 | E14: =B14*'Per-Feature'!D11 -> 0.051 | F14: =B14*'Per-Feature'!E11 -> 0.099
A15: AI voice call (Gemini Live) | B15: 2 | C15: ='Per-Feature'!B12 -> 17 | D15: =B15*C15 -> 34 | E15: =B15*'Per-Feature'!D12 -> 0.026 | F15: =B15*'Per-Feature'!E12 -> 0.044
A16: Voice reply (on-device TTS) | B16: 10 | C16: ='Per-Feature'!B7 -> 20 | D16: =B16*C16 -> 200 | E16: =B16*'Per-Feature'!D7 -> 0 | F16: =B16*'Per-Feature'!E7 -> 0.02
A17: TOTAL / active user / day | B17: coins of 1000 | D17: =SUM(D9:D16) -> 499 | E17: =SUM(E9:E16) -> 0.155 | F17: =SUM(F9:F16) -> 0.3165
A18: …coins used vs 1,000 allowance | D18: =D17&" / "&Assumptions!B5 -> 499 / 1000
A20: C) Projection to all users
A21: Total users | B21: =Assumptions!B7 -> 1000
A22: Daily active users (DAU) | B22: =Assumptions!B7*Assumptions!B8 -> 400
A23: Realistic cost / day (LOW–HIGH) | B23: =B22*E17 -> 62 | C23: =B22*F17 -> 126.6
A24: Realistic cost / month (LOW–HIGH) | B24: =B23*30 -> 1860 | C24: =C23*30 -> 3798
A25: Worst case / month (every DAU maxes translation) | B25: =B22*B4*30 -> 79200
